nblite/__init__.py
nblite/cli/__init__.py
nblite/cli/_helpers.py
nblite/cli/app.py
nblite/cli/commands/__init__.py
nblite/cli/commands/clean.py
nblite/cli/commands/clear.py
nblite/cli/commands/convert.py
nblite/cli/commands/docs.py
nblite/cli/commands/export.py
nblite/cli/commands/fill.py
nblite/cli/commands/from_module.py
nblite/cli/commands/hooks.py
nblite/cli/commands/info.py
nblite/cli/commands/init.py
nblite/cli/commands/list.py
nblite/cli/commands/nb_to_script.py
nblite/cli/commands/new.py
nblite/cli/commands/prepare.py
nblite/cli/commands/readme.py
nblite/cli/commands/templates.py
nblite/config/__init__.py
nblite/config/loader.py
nblite/config/schema.py
nblite/core/__init__.py
nblite/core/cell.py
nblite/core/code_location.py
nblite/core/directive.py
nblite/core/notebook.py
nblite/core/project.py
nblite/core/pyfile.py
nblite/docs/__init__.py
nblite/docs/cell_docs.py
nblite/docs/generator.py
nblite/docs/jupyterbook.py
nblite/docs/mkdocs.py
nblite/docs/process.py
nblite/docs/quarto.py
nblite/docs/readme.py
nblite/export/__init__.py
nblite/export/function_export.py
nblite/export/pipeline.py
nblite/extensions/__init__.py
nblite/extensions/hooks.py
nblite/extensions/loader.py
nblite/fill/__init__.py
nblite/fill/executor.py
nblite/fill/hash.py
nblite/git/__init__.py
nblite/git/hooks.py
nblite/git/staging.py
nblite/readme/__init__.py
nblite/sync/__init__.py
nblite/templates/__init__.py
nblite/templates/renderer.py
nblite/utils/__init__.py
nblite-1.1.10.dist-info/METADATA
nblite-1.1.10.dist-info/WHEEL
nblite-1.1.10.dist-info/entry_points.txt
nblite-1.1.10.dist-info/licenses/LICENSE
nblite-1.1.10.dist-info/RECORD
