Metadata-Version: 2.4
Name: nblite
Version: 1.1.10
Summary: Notebook-driven Python package development tool
Project-URL: Homepage, https://github.com/lukastk/nblite
Project-URL: Documentation, https://github.com/lukastk/nblite
Project-URL: Repository, https://github.com/lukastk/nblite
Author-email: Lukas Kikuchi <lukas@example.com>
License-Expression: MIT
License-File: LICENSE
Keywords: development,jupyter,literate-programming,nbdev,notebook
Classifier: Development Status :: 3 - Alpha
Classifier: Intended Audience :: Developers
Classifier: License :: OSI Approved :: MIT License
Classifier: Programming Language :: Python :: 3
Classifier: Programming Language :: Python :: 3.10
Classifier: Programming Language :: Python :: 3.11
Classifier: Programming Language :: Python :: 3.12
Classifier: Topic :: Software Development :: Libraries :: Python Modules
Requires-Python: >=3.10
Requires-Dist: jinja2>=3.0.0
Requires-Dist: nbconvert>=7.0.0
Requires-Dist: nbformat>=5.0.0
Requires-Dist: notebookx-py>=0.1.8
Requires-Dist: pydantic>=2.0.0
Requires-Dist: pyyaml>=6.0.0
Requires-Dist: rich>=13.0.0
Requires-Dist: tomli>=2.0.0; python_version < '3.11'
Requires-Dist: typer>=0.9.0
Provides-Extra: docs
Requires-Dist: docstring-parser>=0.15; extra == 'docs'
Requires-Dist: jupyter-book>=0.15.0; extra == 'docs'
Requires-Dist: mkdocs-jupyter>=0.24.0; extra == 'docs'
Requires-Dist: mkdocs-material>=9.0.0; extra == 'docs'
Requires-Dist: mkdocs>=1.5.0; extra == 'docs'
